usvisa4uk/__init__.py
usvisa4uk/run.py
usvisa4uk-0.0.1.dist-info/LICENSE
usvisa4uk-0.0.1.dist-info/METADATA
usvisa4uk-0.0.1.dist-info/WHEEL
usvisa4uk-0.0.1.dist-info/top_level.txt
usvisa4uk-0.0.1.dist-info/RECORD
